LICENSE
MANIFEST.in
README.rst
setup.py
django_mail_templated.egg-info/PKG-INFO
django_mail_templated.egg-info/SOURCES.txt
django_mail_templated.egg-info/dependency_links.txt
django_mail_templated.egg-info/top_level.txt
mail_templated/__init__.py
mail_templated/conf.py
mail_templated/default_settings.py
mail_templated/message.py
mail_templated/models.py
mail_templated/tests.py
mail_templated/utils.py
mail_templated/templates/mail_templated/base.tpl
mail_templated/templates/mail_templated_test/alternate_tags.tpl
mail_templated/templates/mail_templated_test/base.tpl
mail_templated/templates/mail_templated_test/empty.tpl
mail_templated/templates/mail_templated_test/extended.tpl
mail_templated/templates/mail_templated_test/multilang.tpl
mail_templated/templates/mail_templated_test/multipart.html
mail_templated/templates/mail_templated_test/overridden.tpl
mail_templated/templates/mail_templated_test/overridden2.tpl
mail_templated/templates/mail_templated_test/plain.html
mail_templated/templates/mail_templated_test/plain.tpl
mail_templated/templates/mail_templated_test/whitespaces.tpl
mail_templated/test_utils/__init__.py
mail_templated/test_utils/attachment.png
mail_templated/test_utils/django_setup.py
mail_templated/test_utils/run.py
mail_templated/test_utils/settings.py
mail_templated/test_utils/settings_extra.py