Metadata-Version: 1.1
Name: django-mail-templated
Version: 2.6.1
Summary: Send emails using Django template system
Home-page: https://github.com/artemrizhov/django-mail-templated
Author: Artem Rizhov
Author-email: artem.rizhov@gmail.com
License: MIT
Platform: any
Classifier: Development Status :: 5 - Production/Stable
Classifier: Intended Audience :: Developers
Classifier: License :: OSI Approved :: MIT License
Classifier: Operating System :: OS Independent
Classifier: Programming Language :: Python
Classifier: Programming Language :: Python :: 2.7
Classifier: Programming Language :: Python :: 3.4
Classifier: Topic :: Software Development :: Libraries :: Python Modules
Classifier: Framework :: Django
